torchserve_client/__init__.py
torchserve_client/_modidx.py
torchserve_client/grpc.py
torchserve_client/rest.py
torchserve_client/proto/__init__.py
torchserve_client/proto/inference_pb2.py
torchserve_client/proto/inference_pb2_grpc.py
torchserve_client/proto/management_pb2.py
torchserve_client/proto/management_pb2_grpc.py
torchserve_client-0.0.2.dist-info/LICENSE
torchserve_client-0.0.2.dist-info/METADATA
torchserve_client-0.0.2.dist-info/WHEEL
torchserve_client-0.0.2.dist-info/entry_points.txt
torchserve_client-0.0.2.dist-info/top_level.txt
torchserve_client-0.0.2.dist-info/RECORD
