Metadata-Version: 2.1
Name: torchserve-client
Version: 0.0.2
Summary: Python Client for TorchServe APIs
Home-page: https://github.com/Ankur-singh/torchserve_client
Author: Ankur Singh
Author-email: as.ankursingh3.1@gmail.com
License: Apache Software License 2.0
Keywords: nbdev jupyter notebook python
Classifier: Development Status :: 4 - Beta
Classifier: Intended Audience :: Developers
Classifier: Natural Language :: English
Classifier: Programming Language :: Python :: 3.7
Classifier: Programming Language :: Python :: 3.8
Classifier: Programming Language :: Python :: 3.9
Classifier: Programming Language :: Python :: 3.10
Classifier: License :: OSI Approved :: Apache Software License
Requires-Python: >=3.7
License-File: LICENSE
Requires-Dist: requests
Requires-Dist: grpcio
Requires-Dist: protobuf
Requires-Dist: grpcio-tools
Provides-Extra: dev
Requires-Dist: black ; extra == 'dev'
Requires-Dist: nbdev ; extra == 'dev'
